{
  "$schema": "https://ui.shadcn.com/schema/registry-item.json",
  "name": "card",
  "type": "registry:ui",
  "title": "Card",
  "files": [
    {
      "path": "src/components/ui/card.tsx",
      "content": "import * as React from \"react\"\n\nimport { cn } from \"@/lib/utils\"\n\nfunction Card({ className, ...props }: React.ComponentProps<\"div\">) {\n  return (\n    <div\n      data-slot=\"card\"\n      className={cn(\n        \"relative rounded-base flex flex-col shadow-shadow-lg border-3 border-border bg-background text-foreground font-base overflow-hidden\",\n        className,\n      )}\n      {...props}\n    />\n  )\n}\n\n// Card with halftone texture overlay\nfunction CardWithTexture({ className, children, ...props }: React.ComponentProps<\"div\">) {\n  return (\n    <Card className={cn(\"\", className)} {...props}>\n      {/* Halftone texture overlay */}\n      <div\n        className=\"absolute inset-0 pointer-events-none z-10 opacity-[0.03] mix-blend-multiply\"\n        style={{\n          backgroundImage: `radial-gradient(circle, currentColor 1px, transparent 1px)`,\n          backgroundSize: \"4px 4px\",\n        }}\n      />\n      {children}\n    </Card>\n  )\n}\n\n// Top decorative bar\nfunction CardBar({ className, variant = \"black\", ...props }: React.ComponentProps<\"div\"> & { variant?: \"black\" | \"red\" | \"gold\" }) {\n  const variantClasses = {\n    black: \"bg-border\",\n    red: \"bg-main\",\n    gold: \"bg-accent\",\n  }\n\n  return (\n    <div\n      data-slot=\"card-bar\"\n      className={cn(\"h-2 w-full\", variantClasses[variant], className)}\n      {...props}\n    />\n  )\n}\n\nfunction CardHeader({ className, ...props }: React.ComponentProps<\"div\">) {\n  return (\n    <div\n      data-slot=\"card-header\"\n      className={cn(\n        \"@container/card-header grid auto-rows-min grid-rows-[auto_auto] items-start gap-1.5 px-6 pt-6 has-[data-slot=card-action]:grid-cols-[1fr_auto] [.border-b]:pb-6\",\n        className,\n      )}\n      {...props}\n    />\n  )\n}\n\nfunction CardTitle({ className, ...props }: React.ComponentProps<\"div\">) {\n  return (\n    <div\n      data-slot=\"card-title\"\n      className={cn(\"font-heading leading-tight uppercase tracking-wider text-lg\", className)}\n      {...props}\n    />\n  )\n}\n\nfunction CardDescription({ className, ...props }: React.ComponentProps<\"div\">) {\n  return (\n    <div\n      data-slot=\"card-description\"\n      className={cn(\"text-sm font-base text-foreground/80\", className)}\n      {...props}\n    />\n  )\n}\n\nfunction CardAction({ className, ...props }: React.ComponentProps<\"div\">) {\n  return (\n    <div\n      data-slot=\"card-action\"\n      className={cn(\n        \"col-start-2 row-span-2 row-start-1 self-start justify-self-end\",\n        className,\n      )}\n      {...props}\n    />\n  )\n}\n\nfunction CardContent({ className, ...props }: React.ComponentProps<\"div\">) {\n  return (\n    <div\n      data-slot=\"card-content\"\n      className={cn(\"px-6 py-4\", className)}\n      {...props}\n    />\n  )\n}\n\nfunction CardFooter({ className, ...props }: React.ComponentProps<\"div\">) {\n  return (\n    <div\n      data-slot=\"card-footer\"\n      className={cn(\"flex items-center px-6 pb-6 [.border-t]:pt-6\", className)}\n      {...props}\n    />\n  )\n}\n\n// Decorative divider for inside cards\nfunction CardDivider({ className, ...props }: React.ComponentProps<\"div\">) {\n  return (\n    <div\n      data-slot=\"card-divider\"\n      className={cn(\"flex items-center gap-2 mx-6 my-4\", className)}\n      {...props}\n    >\n      <div className=\"h-[3px] w-8 bg-border\" />\n      <div className=\"h-[3px] w-3 bg-main\" />\n      <div className=\"h-[3px] flex-1 bg-border\" />\n      <div className=\"w-2 h-2 bg-accent rotate-45\" />\n    </div>\n  )\n}\n\n// Accent badge for card corners (like \"No.01\")\nfunction CardBadge({ className, children, ...props }: React.ComponentProps<\"div\">) {\n  return (\n    <div\n      data-slot=\"card-badge\"\n      className={cn(\n        \"absolute top-4 right-4 w-12 h-12 rounded-full bg-accent border-3 border-border flex items-center justify-center z-20\",\n        className,\n      )}\n      {...props}\n    >\n      <span className=\"text-foreground text-[10px] font-heading tracking-tight uppercase\">\n        {children}\n      </span>\n    </div>\n  )\n}\n\n// Diagonal accent stripe for card corners\nfunction CardAccentStripe({ className, ...props }: React.ComponentProps<\"div\">) {\n  return (\n    <div className={cn(\"absolute top-0 right-0 w-32 h-32 overflow-hidden pointer-events-none\", className)} {...props}>\n      <div className=\"absolute -right-8 -top-8 w-48 h-16 bg-main rotate-45 origin-center transform translate-y-8\" />\n    </div>\n  )\n}\n\nexport {\n  Card,\n  CardWithTexture,\n  CardBar,\n  CardHeader,\n  CardFooter,\n  CardTitle,\n  CardDescription,\n  CardContent,\n  CardAction,\n  CardDivider,\n  CardBadge,\n  CardAccentStripe,\n}\n",
      "type": "registry:ui"
    }
  ]
}